veritastool/config/config.ini
veritastool/config/constants.py
veritastool/metrics/__init__.py
veritastool/metrics/fairness_metrics.py
veritastool/metrics/modelrates.py
veritastool/metrics/newmetric.py
veritastool/metrics/performance_metrics.py
veritastool/metrics/tradeoff.py
veritastool/model/__init__.py
veritastool/model/model_container.py
veritastool/model/modelwrapper.py
veritastool/principles/__init__.py
veritastool/principles/fairness.py
veritastool/principles/transparency.py
veritastool/resources/data/credit_score_dict.pickle
veritastool/resources/data/credit_score_sample.pickle
veritastool/resources/widget/fair_class_jpg.JPG
veritastool/resources/widget/fair_regression_jpg.JPG
veritastool/resources/widget/fair_uplift_jpg.JPG
veritastool/resources/widget/perf_class_jpg.JPG
veritastool/resources/widget/perf_regression_jpg.JPG
veritastool/resources/widget/perf_uplift_jpg.JPG
veritastool/usecases/__init__.py
veritastool/usecases/base_classification.py
veritastool/usecases/base_regression.py
veritastool/usecases/credit_scoring.py
veritastool/usecases/customer_marketing.py
veritastool/usecases/predictive_underwriting.py
veritastool/util/errors.py
veritastool/util/utility.py
veritastool-2.0.2.dist-info/METADATA
veritastool-2.0.2.dist-info/WHEEL
veritastool-2.0.2.dist-info/license.txt
veritastool-2.0.2.dist-info/top_level.txt
veritastool-2.0.2.dist-info/RECORD
