Metadata-Version: 2.1
Name: veritastool
Version: 2.0.2
Summary: Veritas Diagnosis tool for fairness & transparency assessment.
Author: MAS Veritas
License: Apache 2.0
Project-URL: Documentation, https://htmlpreview.github.io/?https://github.com/mas-veritas2/veritastool/blob/main/veritastool/resources/specs/API_Specs_final.html
Project-URL: Source Code, https://github.com/veritas-project/diagnosis-tool
Requires-Python: >=3.8.0,<=3.10.10
License-File: license.txt
Requires-Dist: numpy (==1.23.5)
Requires-Dist: scipy (==1.10.1)
Requires-Dist: scikit-learn (==1.2.2)
Requires-Dist: pandas (==1.5.3)
Requires-Dist: ipywidgets (==8.0.4)
Requires-Dist: ipython (==8.11.0)
Requires-Dist: matplotlib (==3.7.1)
Requires-Dist: tqdm (==4.65.0)
Requires-Dist: phik (==0.12.3)
Requires-Dist: shap (==0.41.0)
Requires-Dist: matplotlib-inline (==0.1.6)
Requires-Dist: pytest (==7.2.2)
Requires-Dist: Jinja2 (==3.1.2)
